configs/test_configs.py
docs/conf.py
docs/requirements.txt
fme/__init__.py
fme/require_gpu.py
fme/sht_fix.py
fme/test_harmonics.py
fme/test_torch.py
fme/ace/__init__.py
fme/ace/evaluator.py
fme/ace/requirements.py
fme/ace/test_ocean_train.py
fme/ace/test_symbols.py
fme/ace/test_train.py
fme/ace/validate_config.py
fme/ace/aggregator/__init__.py
fme/ace/aggregator/null.py
fme/ace/aggregator/plotting.py
fme/ace/aggregator/test_plotting.py
fme/ace/aggregator/test_train.py
fme/ace/aggregator/train.py
fme/ace/aggregator/inference/__init__.py
fme/ace/aggregator/inference/annual.py
fme/ace/aggregator/inference/histogram.py
fme/ace/aggregator/inference/main.py
fme/ace/aggregator/inference/reduced.py
fme/ace/aggregator/inference/seasonal.py
fme/ace/aggregator/inference/spectrum.py
fme/ace/aggregator/inference/test_annual.py
fme/ace/aggregator/inference/test_distributed.py
fme/ace/aggregator/inference/test_evaluator.py
fme/ace/aggregator/inference/test_inference.py
fme/ace/aggregator/inference/test_main.py
fme/ace/aggregator/inference/test_reduced.py
fme/ace/aggregator/inference/test_seasonal.py
fme/ace/aggregator/inference/test_spectrum.py
fme/ace/aggregator/inference/test_time_mean.py
fme/ace/aggregator/inference/test_video.py
fme/ace/aggregator/inference/test_zonal_mean.py
fme/ace/aggregator/inference/time_mean.py
fme/ace/aggregator/inference/video.py
fme/ace/aggregator/inference/zonal_mean.py
fme/ace/aggregator/inference/enso/__init__.py
fme/ace/aggregator/inference/enso/dynamic_index.py
fme/ace/aggregator/inference/enso/enso_coefficient.py
fme/ace/aggregator/inference/enso/historical_index.py
fme/ace/aggregator/inference/enso/test_dynamic_index.py
fme/ace/aggregator/inference/enso/test_enso_coefficient.py
fme/ace/aggregator/one_step/__init__.py
fme/ace/aggregator/one_step/deterministic.py
fme/ace/aggregator/one_step/ensemble.py
fme/ace/aggregator/one_step/main.py
fme/ace/aggregator/one_step/map.py
fme/ace/aggregator/one_step/reduced.py
fme-2026.1.1.dist-info/licenses/LICENSE
fme-2026.1.1.dist-info/METADATA
fme-2026.1.1.dist-info/WHEEL
fme-2026.1.1.dist-info/top_level.txt
fme-2026.1.1.dist-info/RECORD
