Metadata-Version: 2.4
Name: fme
Version: 2026.1.1
Summary: Train and evaluate weather/climate model emulators
Author-email: Ai2 Climate Modeling <climate-public-maintainer@allenai.org>
License:                                  Apache License
Project-URL: Homepage, https://github.com/ai2cm/ace
Project-URL: Documentation, https://ai2-climate-emulator.readthedocs.io/
Keywords: weather,climate,machine learning,emulation
Classifier: Intended Audience :: Science/Research
Classifier: Development Status :: 4 - Beta
Classifier: License :: OSI Approved :: Apache Software License
Classifier: Programming Language :: Python :: 3
Classifier: Topic :: Scientific/Engineering :: Artificial Intelligence
Requires-Python: >=3.11
License-File: LICENSE
Requires-Dist: cartopy>=0.22.0
Requires-Dist: dacite
Requires-Dist: einops>=0.8.1
Requires-Dist: gcsfs
Requires-Dist: h5netcdf
Requires-Dist: h5py
Requires-Dist: imageio>=2.28.1
Requires-Dist: matplotlib
Requires-Dist: moviepy
Requires-Dist: netcdf4
Requires-Dist: numpy
Requires-Dist: omegaconf>=2.1.0
Requires-Dist: pandas
Requires-Dist: plotly
Requires-Dist: s3fs
Requires-Dist: tensorly
Requires-Dist: tensorly-torch
Requires-Dist: torch-harmonics==0.8.0
Requires-Dist: torch>=2
Requires-Dist: wandb[media]>=0.19.0
Requires-Dist: xarray
Requires-Dist: zarr>=3
Provides-Extra: dev
Requires-Dist: coverage[toml]; extra == "dev"
Requires-Dist: pre-commit; extra == "dev"
Requires-Dist: pytest; extra == "dev"
Requires-Dist: pytest-cov; extra == "dev"
Provides-Extra: docs
Requires-Dist: furo==2024.04.27; extra == "docs"
Requires-Dist: sphinx==7.0.0; extra == "docs"
Requires-Dist: sphinx_autodoc_typehints; extra == "docs"
Provides-Extra: deploy
Requires-Dist: build; extra == "deploy"
Requires-Dist: twine; extra == "deploy"
Provides-Extra: graphcast
Requires-Dist: rtree>=1.4.1; extra == "graphcast"
Requires-Dist: trimesh>=4.8.3; extra == "graphcast"
Dynamic: license-file
